{
  "ComponentIndexes": {},
  "ControlUniqueGuids": {},
  "ControlUniqueIds": {
    "App": 1,
    "Button_Back_10": 23,
    "Button_Back_11": 115,
    "Button_Back_3": 7,
    "Button_Back_9": 35,
    "Button_Home_2": 34,
    "Button_Home_3": 22,
    "Button_Home_4": 114,
    "Button1": 146,
    "Gallery_Add_Samples": 40,
    "Gallery_All_Filters": 107,
    "Gallery_CoA_Scanner_1": 13,
    "Gallery_CoA_Selected_1": 9,
    "Gallery_Other_1": 17,
    "Gallery_Results_Main": 62,
    "Gallery_Select_Material": 37,
    "Gallery_Select_Sampling_Point": 44,
    "Gallery_Spec_High": 56,
    "Gallery_Spec_High_1": 124,
    "Gallery_Spec_Low": 59,
    "Gallery_Spec_Low_1": 127,
    "Gallery_Tests_Add_Sample": 104,
    "Gallery_Tests_Inner": 67,
    "Gallery_Tests_Large": 47,
    "Gallery_Tests_Main": 50,
    "Gallery_Tests_Main_1": 140,
    "Gallery_Title_Caustic": 117,
    "Gallery_Units": 53,
    "Gallery_Units_1": 120,
    "Gallery2": 130,
    "galleryTemplate1_1": 54,
    "galleryTemplate1_11": 121,
    "galleryTemplate1_12": 118,
    "galleryTemplate1_13": 51,
    "galleryTemplate1_14": 141,
    "galleryTemplate1_17": 106,
    "galleryTemplate1_2": 48,
    "galleryTemplate1_3": 57,
    "galleryTemplate1_4": 60,
    "galleryTemplate1_6": 69,
    "galleryTemplate1_8": 128,
    "galleryTemplate1_9": 125,
    "galleryTemplate2": 131,
    "galleryTemplate3": 63,
    "galleryTemplate3_11": 41,
    "galleryTemplate3_13": 108,
    "galleryTemplate3_2": 10,
    "galleryTemplate3_3": 14,
    "galleryTemplate3_6": 18,
    "galleryTemplate3_7": 39,
    "galleryTemplate3_9": 45,
    "Group2": 110,
    "Hide_add_sample": 33,
    "Host": 3,
    "HtmlText1_1": 49,
    "HtmlText1_4": 105,
    "Label_a": 101,
    "Label_AA": 98,
    "Label_All_Test_Filter": 28,
    "Label_b": 102,
    "Label_Bag_Batch_Number": 96,
    "Label_Bag_Number": 89,
    "Label_Batch_Number": 87,
    "Label_Bulk_Density": 76,
    "Label_Caustic": 75,
    "Label_Caustic_Date": 135,
    "Label_Caustic_Material_Main": 132,
    "Label_Caustic_Result": 138,
    "Label_Caustic_Sample_Point": 134,
    "Label_Caustic_Time": 136,
    "Label_Comment": 82,
    "Label_Composition": 90,
    "Label_Crystalisation": 80,
    "Label_Data_1": 68,
    "Label_Date": 88,
    "Label_Ext_b": 92,
    "Label_Extruder_IV": 71,
    "Label_Fines": 85,
    "Label_Float_Sink": 86,
    "Label_GC": 70,
    "Label_Glass": 77,
    "Label_Inclusions": 93,
    "Label_Inclusions_Large": 94,
    "Label_Inclusions_Medium": 97,
    "Label_IV_MFI": 83,
    "Label_L": 100,
    "Label_Lab": 91,
    "Label_Limonene": 99,
    "Label_Material": 72,
    "Label_Material_Density": 84,
    "Label_Metal": 64,
    "Label_Moisture": 73,
    "Label_Pellet_Count_1g": 103,
    "Label_Pellet_Count_5g": 65,
    "Label_PET": 78,
    "Label_pH": 81,
    "Label_PVC": 79,
    "Label_Sample_Point": 74,
    "Label_Sampling_Point": 46,
    "Label_Sampling_Point_2": 42,
    "Label_Time": 95,
    "Label_Visual_Inspection": 66,
    "Label1": 11,
    "Label1_1": 15,
    "Label1_4": 19,
    "Label1_5": 38,
    "Label1_7": 109,
    "Label2": 123,
    "Label3": 145,
    "Label5_1": 55,
    "Label5_10": 52,
    "Label5_11": 142,
    "Label5_2": 58,
    "Label5_3": 61,
    "Label5_5": 129,
    "Label5_6": 126,
    "Label5_8": 122,
    "Label5_9": 119,
    "Loading": 6,
    "Refresh_Data_1": 36,
    "Refresh_Data_2": 24,
    "Refresh_Data_3": 116,
    "Screen_Start": 4,
    "Screen_Test_Caustic_Strength": 112,
    "Screen_Test_input": 25,
    "Screen_Under_Construction": 20,
    "Select_Button_Background": 43,
    "Show_add_sample": 32,
    "Test_1": 31,
    "Test_2": 30,
    "Test_3": 29,
    "Test_boxes": 111,
    "Test_Button_add_samples": 27,
    "TextInput_Caustic_Comment": 139,
    "TextInput_Caustic_Titration": 137,
    "Title_2": 5,
    "Title_3": 8,
    "Title_4": 12,
    "Title_5": 16,
    "Title_pH": 143,
    "Title_Test_Input": 26,
    "Title_Test_Input_1": 21,
    "Title_Test_Input_2": 113
  },
  "FunctionParamsInvariantScripts": {},
  "FunctionParamsInvariantScriptsOnInstances": {},
  "HeaderLastSavedDateTimeUTC": "11/21/2023 16:20:28",
  "IsLegacyComponentAllowGlobalScopeCase": false,
  "LocalConnectionIDReferences": {
    "0710b7fd-091c-4334-953f-c692b65a8149": "\"/providers/microsoft.powerapps/apis/shared_sharepointonline/connections/3e58f23e33004ca9bf262302f462b7a6\"",
    "d1ea80bf-1ad3-47c3-a3f4-abf1be99ed07": "\"/providers/microsoft.powerapps/apis/shared_excelonlinebusiness/connections/cf1bc862b390431a9a648f979a1495ba\""
  },
  "LocalDatabaseReferencesAsEmpty": false,
  "LocalResourceFileNames": {
    "CoA_Banner": "0001.bmp",
    "CoA_Banner_HDPE_Natural": "0002.bmp",
    "CoA_Banner_PET": "0003.bmp",
    "CoA_Banner_PET_Flake": "0004.bmp",
    "CoA_Banner_PP": "0005.bmp"
  },
  "LocalResourceRootPaths": {
    "CoA_Banner": "https://docserverpwaprodweu.blob.core.windows.net/f00cdee1-f59b-4b49-b031-fd7bbea013d7-1/resource/Assets0Images00001.bmp?skoid=58690ece-ec83-4ce2-9ce8-883d4d6a54ee&sktid=975f013f-7f24-47e8-a7d3-abc4752bf346&skt=2023-11-21T12%3A10%3A57Z&ske=2023-11-22T12%3A25%3A57Z&sks=b&skv=2021-12-02&sv=2021-12-02&spr=https&se=2023-11-22T12%3A25%3A57Z&sr=b&sp=r&sig=9csUaWY9ufEuySimkX%2F5agAR7K6PcyPPePyIKOxlQzs%3D",
    "CoA_Banner_HDPE_Natural": "https://docserverpwaprodweu.blob.core.windows.net/f00cdee1-f59b-4b49-b031-fd7bbea013d7-1/resource/Assets0Images00002.bmp?skoid=58690ece-ec83-4ce2-9ce8-883d4d6a54ee&sktid=975f013f-7f24-47e8-a7d3-abc4752bf346&skt=2023-11-21T12%3A10%3A57Z&ske=2023-11-22T12%3A25%3A57Z&sks=b&skv=2021-12-02&sv=2021-12-02&spr=https&se=2023-11-22T12%3A25%3A57Z&sr=b&sp=r&sig=dFo%2FF2uYwXUzbnd1EkNDIgwaJpfG4mxHBe7sHzNlU6g%3D",
    "CoA_Banner_PET": "https://docserverpwaprodweu.blob.core.windows.net/f00cdee1-f59b-4b49-b031-fd7bbea013d7-1/resource/Assets0Images00003.bmp?skoid=58690ece-ec83-4ce2-9ce8-883d4d6a54ee&sktid=975f013f-7f24-47e8-a7d3-abc4752bf346&skt=2023-11-21T12%3A10%3A57Z&ske=2023-11-22T12%3A25%3A57Z&sks=b&skv=2021-12-02&sv=2021-12-02&spr=https&se=2023-11-22T12%3A25%3A57Z&sr=b&sp=r&sig=KEEY%2BEMBUdAisVtrYATTW0wtFh37GqRhV6wxMY2OhMo%3D",
    "CoA_Banner_PET_Flake": "https://docserverpwaprodweu.blob.core.windows.net/f00cdee1-f59b-4b49-b031-fd7bbea013d7-1/resource/Assets0Images00004.bmp?skoid=58690ece-ec83-4ce2-9ce8-883d4d6a54ee&sktid=975f013f-7f24-47e8-a7d3-abc4752bf346&skt=2023-11-21T12%3A10%3A57Z&ske=2023-11-22T12%3A25%3A57Z&sks=b&skv=2021-12-02&sv=2021-12-02&spr=https&se=2023-11-22T12%3A25%3A57Z&sr=b&sp=r&sig=jpAC%2FP5YwInsHnVjxL5XsoH6N2zpuev2QBy1S0Axrv8%3D",
    "CoA_Banner_PP": "https://docserverpwaprodweu.blob.core.windows.net/f00cdee1-f59b-4b49-b031-fd7bbea013d7-1/resource/Assets0Images00005.bmp?skoid=58690ece-ec83-4ce2-9ce8-883d4d6a54ee&sktid=975f013f-7f24-47e8-a7d3-abc4752bf346&skt=2023-11-21T12%3A10%3A57Z&ske=2023-11-22T12%3A25%3A57Z&sks=b&skv=2021-12-02&sv=2021-12-02&spr=https&se=2023-11-22T12%3A25%3A57Z&sr=b&sp=r&sig=LybF90jjKcxnahPCc52kuGoKhNgFfQmIpJ3%2BjUCr8jo%3D"
  },
  "OldLogoFileName": "logo.jpg",
  "OrderComponentMetadata": {},
  "OrderComponentTemplate": {},
  "OrderDataSource": {
    "col_All_All": 38,
    "col_All_Flake_Bag": 36,
    "col_All_Pellet_Bag": 32,
    "col_All_Post_Extruder": 34,
    "col_All_Post_Flake_Sorter": 35,
    "col_All_Sampling_Silo": 31,
    "col_All_SSP": 33,
    "col_All_Wash": 37,
    "col_Caustic_Updates": 39,
    "col_Error": 4,
    "col_HDPE_Nat_All": 22,
    "col_HDPE_Nat_Pellet_Bag": 18,
    "col_HDPE_Nat_Post_Extruder": 19,
    "col_HDPE_Nat_Post_Flake_Sorter": 20,
    "col_HDPE_Nat_Sampling_Silo": 17,
    "col_HDPE_Nat_Wash": 21,
    "col_HDPE_SC_All": 16,
    "col_HDPE_SC_Pellet_Bag": 12,
    "col_HDPE_SC_Post_Extruder": 13,
    "col_HDPE_SC_Post_Flake_Sorter": 14,
    "col_HDPE_SC_Sampling_Silo": 11,
    "col_HDPE_SC_Wash": 15,
    "col_PET_All": 30,
    "col_PET_Flake_Bag": 28,
    "col_PET_Pellet_Bag": 24,
    "col_PET_Post_Extruder": 26,
    "col_PET_Post_Flake_Sorter": 27,
    "col_PET_Sampling_Silo": 23,
    "col_PET_SSP": 25,
    "col_PET_Wash": 29,
    "col_PP_All": 10,
    "col_PP_Pellet_Bag": 6,
    "col_PP_Post_Extruder": 7,
    "col_PP_Post_Flake_Sorter": 8,
    "col_PP_Sampling_Silo": 5,
    "col_PP_Wash": 9,
    "CustomGallerySample": 0,
    "DropDownSample": 1,
    "Table_Specifications": 3,
    "Test Results": 2
  },
  "OrderGroupControls": {
    "Group2": {
      "Button_Back_9": 2,
      "Button_Home_2": 1,
      "Refresh_Data_1": 0,
      "Title_Test_Input": 3
    },
    "Test_boxes": {
      "Test_1": 2,
      "Test_2": 1,
      "Test_3": 0
    },
    "Title_pH": {
      "Button_Back_11": 1,
      "Button_Home_4": 2,
      "Refresh_Data_3": 3,
      "Title_Test_Input_2": 0
    }
  },
  "OrderPcfTemplate": {},
  "OrderTemplate": {},
  "OrderXMLTemplate": {
    "button": 3,
    "gallery": 2,
    "htmlViewer": 4,
    "icon": 1,
    "label": 0,
    "text": 5
  },
  "OverridablePropertiesEntry": {
    "App": {},
    "Button_Back_10": {},
    "Button_Back_11": {},
    "Button_Back_3": {},
    "Button_Back_9": {},
    "Button_Home_2": {},
    "Button_Home_3": {},
    "Button_Home_4": {},
    "Button1": {},
    "Gallery_Add_Samples": {},
    "Gallery_All_Filters": {},
    "Gallery_CoA_Scanner_1": {},
    "Gallery_CoA_Selected_1": {},
    "Gallery_Other_1": {},
    "Gallery_Results_Main": {},
    "Gallery_Select_Material": {},
    "Gallery_Select_Sampling_Point": {},
    "Gallery_Spec_High": {},
    "Gallery_Spec_High_1": {},
    "Gallery_Spec_Low": {},
    "Gallery_Spec_Low_1": {},
    "Gallery_Tests_Add_Sample": {},
    "Gallery_Tests_Inner": {},
    "Gallery_Tests_Large": {},
    "Gallery_Tests_Main": {},
    "Gallery_Tests_Main_1": {},
    "Gallery_Title_Caustic": {},
    "Gallery_Units": {},
    "Gallery_Units_1": {},
    "Gallery2": {},
    "galleryTemplate1_1": {},
    "galleryTemplate1_11": {},
    "galleryTemplate1_12": {},
    "galleryTemplate1_13": {},
    "galleryTemplate1_14": {},
    "galleryTemplate1_17": {},
    "galleryTemplate1_2": {},
    "galleryTemplate1_3": {},
    "galleryTemplate1_4": {},
    "galleryTemplate1_6": {},
    "galleryTemplate1_8": {},
    "galleryTemplate1_9": {},
    "galleryTemplate2": {},
    "galleryTemplate3": {},
    "galleryTemplate3_11": {},
    "galleryTemplate3_13": {},
    "galleryTemplate3_2": {},
    "galleryTemplate3_3": {},
    "galleryTemplate3_6": {},
    "galleryTemplate3_7": {},
    "galleryTemplate3_9": {},
    "Group2": {},
    "Hide_add_sample": {},
    "Host": {},
    "HtmlText1_1": {},
    "HtmlText1_4": {},
    "Label_a": {},
    "Label_AA": {},
    "Label_All_Test_Filter": {},
    "Label_b": {},
    "Label_Bag_Batch_Number": {},
    "Label_Bag_Number": {},
    "Label_Batch_Number": {},
    "Label_Bulk_Density": {},
    "Label_Caustic": {},
    "Label_Caustic_Date": {},
    "Label_Caustic_Material_Main": {},
    "Label_Caustic_Result": {},
    "Label_Caustic_Sample_Point": {},
    "Label_Caustic_Time": {},
    "Label_Comment": {},
    "Label_Composition": {},
    "Label_Crystalisation": {},
    "Label_Data_1": {},
    "Label_Date": {},
    "Label_Ext_b": {},
    "Label_Extruder_IV": {},
    "Label_Fines": {},
    "Label_Float_Sink": {},
    "Label_GC": {},
    "Label_Glass": {},
    "Label_Inclusions": {},
    "Label_Inclusions_Large": {},
    "Label_Inclusions_Medium": {},
    "Label_IV_MFI": {},
    "Label_L": {},
    "Label_Lab": {},
    "Label_Limonene": {},
    "Label_Material": {},
    "Label_Material_Density": {},
    "Label_Metal": {},
    "Label_Moisture": {},
    "Label_Pellet_Count_1g": {},
    "Label_Pellet_Count_5g": {},
    "Label_PET": {},
    "Label_pH": {},
    "Label_PVC": {},
    "Label_Sample_Point": {},
    "Label_Sampling_Point": {},
    "Label_Sampling_Point_2": {},
    "Label_Time": {},
    "Label_Visual_Inspection": {},
    "Label1": {},
    "Label1_1": {},
    "Label1_4": {},
    "Label1_5": {},
    "Label1_7": {},
    "Label2": {},
    "Label3": {},
    "Label5_1": {},
    "Label5_10": {},
    "Label5_11": {},
    "Label5_2": {},
    "Label5_3": {},
    "Label5_5": {},
    "Label5_6": {},
    "Label5_8": {},
    "Label5_9": {},
    "Loading": {},
    "Refresh_Data_1": {},
    "Refresh_Data_2": {},
    "Refresh_Data_3": {},
    "Screen_Start": {},
    "Screen_Test_Caustic_Strength": {},
    "Screen_Test_input": {},
    "Screen_Under_Construction": {},
    "Select_Button_Background": {},
    "Show_add_sample": {},
    "Test_1": {},
    "Test_2": {},
    "Test_3": {},
    "Test_boxes": {},
    "Test_Button_add_samples": {},
    "TextInput_Caustic_Comment": {},
    "TextInput_Caustic_Titration": {},
    "Title_2": {},
    "Title_3": {},
    "Title_4": {},
    "Title_5": {},
    "Title_pH": {},
    "Title_Test_Input": {},
    "Title_Test_Input_1": {},
    "Title_Test_Input_2": {}
  },
  "PCFDynamicSchemaForIRRetrievalEntry": {},
  "PCFTemplateEntry": {},
  "PublishOrderIndices": {
    "App": 0,
    "Button_Back_10": 135,
    "Button_Back_11": 105,
    "Button_Back_3": 2,
    "Button_Back_9": 26,
    "Button_Home_2": 25,
    "Button_Home_3": 134,
    "Button_Home_4": 104,
    "Button1": 129,
    "Gallery_Add_Samples": 31,
    "Gallery_All_Filters": 98,
    "Gallery_CoA_Scanner_1": 8,
    "Gallery_CoA_Selected_1": 4,
    "Gallery_Other_1": 12,
    "Gallery_Results_Main": 53,
    "Gallery_Select_Material": 28,
    "Gallery_Select_Sampling_Point": 35,
    "Gallery_Spec_High": 47,
    "Gallery_Spec_High_1": 114,
    "Gallery_Spec_Low": 50,
    "Gallery_Spec_Low_1": 117,
    "Gallery_Tests_Add_Sample": 95,
    "Gallery_Tests_Inner": 58,
    "Gallery_Tests_Large": 38,
    "Gallery_Tests_Main": 41,
    "Gallery_Tests_Main_1": 130,
    "Gallery_Title_Caustic": 107,
    "Gallery_Units": 44,
    "Gallery_Units_1": 110,
    "Gallery2": 120,
    "galleryTemplate1_1": 45,
    "galleryTemplate1_11": 111,
    "galleryTemplate1_12": 108,
    "galleryTemplate1_13": 42,
    "galleryTemplate1_14": 131,
    "galleryTemplate1_17": 97,
    "galleryTemplate1_2": 39,
    "galleryTemplate1_3": 48,
    "galleryTemplate1_4": 51,
    "galleryTemplate1_6": 60,
    "galleryTemplate1_8": 118,
    "galleryTemplate1_9": 115,
    "galleryTemplate2": 121,
    "galleryTemplate3": 54,
    "galleryTemplate3_11": 32,
    "galleryTemplate3_13": 99,
    "galleryTemplate3_2": 5,
    "galleryTemplate3_3": 9,
    "galleryTemplate3_6": 13,
    "galleryTemplate3_7": 30,
    "galleryTemplate3_9": 36,
    "Group2": 17,
    "Hide_add_sample": 24,
    "Host": 0,
    "HtmlText1_1": 40,
    "HtmlText1_4": 96,
    "Label_a": 92,
    "Label_AA": 89,
    "Label_All_Test_Filter": 18,
    "Label_b": 93,
    "Label_Bag_Batch_Number": 87,
    "Label_Bag_Number": 80,
    "Label_Batch_Number": 78,
    "Label_Bulk_Density": 67,
    "Label_Caustic": 66,
    "Label_Caustic_Date": 124,
    "Label_Caustic_Material_Main": 122,
    "Label_Caustic_Result": 127,
    "Label_Caustic_Sample_Point": 123,
    "Label_Caustic_Time": 125,
    "Label_Comment": 73,
    "Label_Composition": 81,
    "Label_Crystalisation": 71,
    "Label_Data_1": 59,
    "Label_Date": 79,
    "Label_Ext_b": 83,
    "Label_Extruder_IV": 62,
    "Label_Fines": 76,
    "Label_Float_Sink": 77,
    "Label_GC": 61,
    "Label_Glass": 68,
    "Label_Inclusions": 84,
    "Label_Inclusions_Large": 85,
    "Label_Inclusions_Medium": 88,
    "Label_IV_MFI": 74,
    "Label_L": 91,
    "Label_Lab": 82,
    "Label_Limonene": 90,
    "Label_Material": 63,
    "Label_Material_Density": 75,
    "Label_Metal": 55,
    "Label_Moisture": 64,
    "Label_Pellet_Count_1g": 94,
    "Label_Pellet_Count_5g": 56,
    "Label_PET": 69,
    "Label_pH": 72,
    "Label_PVC": 70,
    "Label_Sample_Point": 65,
    "Label_Sampling_Point": 37,
    "Label_Sampling_Point_2": 33,
    "Label_Time": 86,
    "Label_Visual_Inspection": 57,
    "Label1": 6,
    "Label1_1": 10,
    "Label1_4": 14,
    "Label1_5": 29,
    "Label1_7": 100,
    "Label2": 113,
    "Label3": 103,
    "Label5_1": 46,
    "Label5_10": 43,
    "Label5_11": 132,
    "Label5_2": 49,
    "Label5_3": 52,
    "Label5_5": 119,
    "Label5_6": 116,
    "Label5_8": 112,
    "Label5_9": 109,
    "Loading": 1,
    "Refresh_Data_1": 27,
    "Refresh_Data_2": 136,
    "Refresh_Data_3": 106,
    "Screen_Start": 6,
    "Screen_Test_Caustic_Strength": 6,
    "Screen_Test_input": 22,
    "Screen_Under_Construction": 6,
    "Select_Button_Background": 34,
    "Show_add_sample": 23,
    "Test_1": 22,
    "Test_2": 21,
    "Test_3": 19,
    "Test_boxes": 20,
    "Test_Button_add_samples": 16,
    "TextInput_Caustic_Comment": 128,
    "TextInput_Caustic_Titration": 126,
    "Title_2": 0,
    "Title_3": 3,
    "Title_4": 7,
    "Title_5": 11,
    "Title_pH": 102,
    "Title_Test_Input": 15,
    "Title_Test_Input_1": 133,
    "Title_Test_Input_2": 101
  },
  "ResourcesJsonIndices": {
    "Image-CoA_Banner": 2,
    "Image-CoA_Banner_HDPE_Natural": 3,
    "Image-CoA_Banner_PET": 4,
    "Image-CoA_Banner_PET_Flake": 5,
    "Image-CoA_Banner_PP": 6,
    "Image-SampleImage": 0,
    "Pdf-SamplePdf": 1
  },
  "RuleScreenIdWithoutScreen": {},
  "TemplateVersions": {},
  "VolatileProperties": {
    "AnalysisLoadTime": 0.848107,
    "ControlCount": {
      "button": 1,
      "gallery": 21,
      "galleryTemplate": 21,
      "group": 3,
      "htmlViewer": 2,
      "icon": 12,
      "label": 73,
      "PowerApps_CoreControls_ButtonCanvas": 1,
      "screen": 4,
      "text": 2
    },
    "DeserializationLoadTime": 2.981785
  },
  "WasLocalDatabaseReferencesEmpty": true
}